aos_starter/__init__.py
aos_starter/actions.py
aos_starter/main.py
aos_starter-0.0.9.dist-info/METADATA
aos_starter-0.0.9.dist-info/WHEEL
aos_starter-0.0.9.dist-info/entry_points.txt
aos_starter-0.0.9.dist-info/top_level.txt
aos_starter-0.0.9.dist-info/RECORD
